tft/cli/__init__.py
tft/cli/command/__init__.py
tft/cli/command/listing.py
tft/cli/commands.py
tft/cli/config.py
tft/cli/tool.py
tft/cli/utils.py
tft_cli-0.0.29.dist-info/LICENSE
tft_cli-0.0.29.dist-info/METADATA
tft_cli-0.0.29.dist-info/WHEEL
tft_cli-0.0.29.dist-info/entry_points.txt
tft_cli-0.0.29.dist-info/RECORD
