Metadata-Version: 2.1
Name: tft-cli
Version: 0.0.29
Summary: Testing Farm CLI tool
License: Apache-2.0
Author: Miroslav Vadkerti
Author-email: mvadkert@redhat.com
Requires-Python: >=3.9,<4.0
Classifier: License :: OSI Approved :: Apache Software License
Classifier: Programming Language :: Python :: 3
Classifier: Programming Language :: Python :: 3.9
Classifier: Programming Language :: Python :: 3.10
Classifier: Programming Language :: Python :: 3.11
Requires-Dist: click (>=8.0.4,<9.0.0)
Requires-Dist: colorama (>=0.4.4,<0.5.0)
Requires-Dist: dynaconf (>=3.1.2,<4.0.0)
Requires-Dist: pendulum (>=3.0.0,<4.0.0)
Requires-Dist: requests (>=2.27.1,<3.0.0)
Requires-Dist: rich (>=12)
Requires-Dist: ruamel-yaml (>=0.18.5,<0.19.0)
Requires-Dist: setuptools
Requires-Dist: shellingham (>=1.3.0,<2.0.0)
Requires-Dist: typer (>=0.11)
